proxtor/Dockerfile
proxtor/main.py
proxtor/tests.py
proxtor-1.0.0.dist-info/LICENSE
proxtor-1.0.0.dist-info/METADATA
proxtor-1.0.0.dist-info/WHEEL
proxtor-1.0.0.dist-info/RECORD
