Metadata-Version: 2.1
Name: proxtor
Version: 1.0.0
Summary: A simple python proxy for Tor
Home-page: https://github.com/GraphtyLove/python_tor_proxy
License: MIT
Author: GraphtyLove
Author-email: maxim.berge@gmail.com
Requires-Python: >=3.7,<4.0
Classifier: Intended Audience :: Developers
Classifier: License :: OSI Approved :: MIT License
Classifier: Operating System :: OS Independent
Classifier: Programming Language :: Python
Classifier: Programming Language :: Python :: 3
Classifier: Programming Language :: Python :: 3.7
Classifier: Programming Language :: Python :: 3.8
Classifier: Programming Language :: Python :: 3.9
Classifier: Programming Language :: Python :: 3.10
Classifier: Programming Language :: Python :: 3.11
Classifier: Programming Language :: Python :: 3 :: Only
Classifier: Typing :: Typed
Requires-Dist: redis (==4.3.4)
Project-URL: Repository, https://github.com/GraphtyLove/python_tor_proxy
